Metadata-Version: 1.0
Name: welford
Version: 0.2.3
Summary: Python (numpy) implementation of Welford's algorithm.
Home-page: https://github.com/a-mitani/welford
Author: Akira Mitani
Author-email: amitani.public@gmail.com
License: MIT
Keywords: statistics,online,welford
Platform: UNKNOWN
